configen/__init__.py
configen/api.py
configen/decoder.py
configen/main.py
configen/property.py
configen/runner.py
configen/system.py
configen_cli-0.1.16.dist-info/METADATA
configen_cli-0.1.16.dist-info/WHEEL
configen_cli-0.1.16.dist-info/entry_points.txt
configen_cli-0.1.16.dist-info/RECORD
