Metadata-Version: 2.3
Name: configen-cli
Version: 0.1.16
Summary: Configen cli
Author: kostyarypta
Author-email: kostya.rypta@gmail.com
Requires-Python: >=3.12,<4.0
Classifier: Programming Language :: Python :: 3
Classifier: Programming Language :: Python :: 3.12
Classifier: Programming Language :: Python :: 3.13
Requires-Dist: backoff (>=2.2.1,<3.0.0)
Requires-Dist: fastapi (>=0.115.0,<0.116.0)
Requires-Dist: httpx (>=0.27.0,<0.28.0)
Requires-Dist: openai (>=1.30.1,<2.0.0)
Requires-Dist: pexpect (>=4.9.0,<5.0.0)
Requires-Dist: platformdirs (>=4.3.1,<5.0.0)
Requires-Dist: psutil (>=5.9.8,<6.0.0)
Requires-Dist: python-dotenv (>=1.0.1,<2.0.0)
Requires-Dist: rich (>=13.7.1,<14.0.0)
Requires-Dist: tqdm (>=4.66.4,<5.0.0)
Requires-Dist: typer (>=0.12.3,<0.13.0)
